pyja_geocoder/__init__.py
pyja_geocoder/constants.py
pyja_geocoder/data_fetcher.py
pyja_geocoder/geocode.py
pyja_geocoder-0.1.3.dist-info/LICENSE
pyja_geocoder-0.1.3.dist-info/METADATA
pyja_geocoder-0.1.3.dist-info/WHEEL
pyja_geocoder-0.1.3.dist-info/top_level.txt
pyja_geocoder-0.1.3.dist-info/RECORD
