Metadata-Version: 2.1
Name: pyja-geocoder
Version: 0.1.3
Summary: A fast vectorized reverse geocoding tool with GeoPandas
Author-email: Kosaku Nakano <nakanokosaku@gmail.com>
License: MIT
Project-URL: Source Code, https://github.com/nkosaku/pyja_geocoder
Project-URL: Documentation, https://github.com/nkosaku/pyja_geocoder#readme
Keywords: reverse geocoding,geopandas,japan,address
Classifier: Programming Language :: Python :: 3
Classifier: License :: OSI Approved :: MIT License
Classifier: Operating System :: OS Independent
License-File: LICENSE
Requires-Dist: geopandas>=0.10
Requires-Dist: pyproj
Requires-Dist: shapely>=2.0
Requires-Dist: requests
